{
    "version": "2.0",
    "metadata": {
        "apiVersion": "2016-12-20",
        "endpointPrefix": "execute-api",
        "protocol": "json",
        "serviceFullName": "VitalServices"
    },
    "operations": {
        "updateUser": {
            "name": "updateUser",
            "http": {
                "method": "POST",
                "requestUri": "/prod/update-user",
                "responseCode": 200
            },
            "input": {
                "shape": "UpdateUserRequest"
            },
            "output": {
                "shape": "ClientUser"
            }
        },
        "searchForDoctors": {
            "name": "searchForDoctors",
            "http": {
                "method": "POST",
                "requestUri": "/prod/search-for-doctors",
                "responseCode": 200
            },
            "input": {
                "shape": "SearchForDoctorsRequest"
            },
            "output": {
                "shape": "SearchForDoctorsResult"
            }
        },
        "urlForFile": {
            "name": "urlForFile",
            "http": {
                "method": "POST",
                "requestUri": "/prod/url-for-file",
                "responseCode": 200
            },
            "input": {
                "shape": "UrlForFileRequest"
            },
            "output": {
                "shape": "UrlForFileResult"
            }
        },
        "queryDoctorSchedule": {
            "name": "queryDoctorSchedule",
            "http": {
                "method": "POST",
                "requestUri": "/prod/query-doctor-schedule",
                "responseCode": 200
            },
            "input": {
                "shape": "QueryDoctorScheduleRequest"
            },
            "output": {
                "shape": "QueryDoctorScheduleResult"
            }
        },
        "addCreditCard": {
            "name": "addCreditCard",
            "http": {
                "method": "POST",
                "requestUri": "/prod/add-credit-card",
                "responseCode": 200
            },
            "input": {
                "shape": "AddCreditCardRequest"
            },
            "output": {
                "shape": "Empty"
            }
        },
        "scheduleAppointment": {
            "name": "scheduleAppointment",
            "http": {
                "method": "POST",
                "requestUri": "/prod/schedule-appointment",
                "responseCode": 200
            },
            "input": {
                "shape": "ScheduleAppointmentRequest"
            },
            "output": {
                "shape": "ScheduleAppointmentResult"
            }
        },
        "cancelAppointment": {
            "name": "cancelAppointment",
            "http": {
                "method": "POST",
                "requestUri": "/prod/cancel-appointment",
                "responseCode": 200
            },
            "input": {
                "shape": "CancelAppointmentRequest"
            },
            "output": {
                "shape": "CancelAppointmentResult"
            }
        },
        "getStripeCustomer": {
            "name": "getStripeCustomer",
            "http": {
                "method": "POST",
                "requestUri": "/prod/get-stripe-customer",
                "responseCode": 200
            },
            "input": {
                "shape": "GetStripeCustomerRequest"
            },
            "output": {
                "shape": "StripeObject"
            }
        },
        "getAppointmentPaymentMethod": {
            "name": "getAppointmentPaymentMethod",
            "http": {
                "method": "POST",
                "requestUri": "/prod/get-appointment-payment-method",
                "responseCode": 200
            },
            "input": {
                "shape": "GetAppointmentPaymentMethodRequest"
            },
            "output": {
                "shape": "StripeObject"
            }
        },
        "setDefaultPaymentSource": {
            "name": "setDefaultPaymentSource",
            "http": {
                "method": "POST",
                "requestUri": "/prod/set-default-payment-source",
                "responseCode": 200
            },
            "input": {
                "shape": "SetDefaultPaymentSourceRequest"
            },
            "output": {
                "shape": "Empty"
            }
        },
        "getAppointmentsWithUser": {
            "name": "getAppointmentsWithUser",
            "http": {
                "method": "POST",
                "requestUri": "/prod/get-appointments-with-user",
                "responseCode": 200
            },
            "input": {
                "shape": "GetAppointmentsWithUserRequest"
            },
            "output": {
                "shape": "GetAppointmentsResult"
            }
        },
        "registerUser": {
            "name": "registerUser",
            "http": {
                "method": "POST",
                "requestUri": "/prod/register-user",
                "responseCode": 200
            },
            "input": {
                "shape": "RegisterUserRequest"
            },
            "output": {
                "shape": "ClientUser"
            }
        },
        "getAppointmentBill": {
            "name": "getAppointmentBill",
            "http": {
                "method": "POST",
                "requestUri": "/prod/get-appointment-bill",
                "responseCode": 200
            },
            "input": {
                "shape": "GetAppointmentBillRequest"
            },
            "output": {
                "shape": "ClientAppointmentBill"
            }
        },
        "getLoggedInUser": {
            "name": "getLoggedInUser",
            "http": {
                "method": "POST",
                "requestUri": "/prod/get-logged-in-user",
                "responseCode": 200
            },
            "input": {
                "shape": "VitalServicesRequest"
            },
            "output": {
                "shape": "GetLoggedInUserResult"
            }
        },
        "getDoctors": {
            "name": "getDoctors",
            "http": {
                "method": "POST",
                "requestUri": "/prod/get-doctors",
                "responseCode": 200
            },
            "input": {
                "shape": "GetDoctorsRequest"
            },
            "output": {
                "shape": "GetDoctorsResult"
            }
        }
    },
    "shapes": {
        "AddCreditCardRequest_cardToken": {
            "type": "string"
        },
        "AddCreditCardRequest": {
            "type": "structure",
            "required": [
                "cardToken"
            ],
            "members": {
                "cardToken": {
                    "shape": "AddCreditCardRequest_cardToken"
                }
            }
        },
        "GetDoctorsRequest_doctorIdsItem": {
            "type": "string"
        },
        "GetDoctorsRequest_doctorIds": {
            "type": "list",
            "member": {
                "shape": "GetDoctorsRequest_doctorIdsItem"
            }
        },
        "GetDoctorsRequest": {
            "type": "structure",
            "required": [],
            "members": {
                "doctorIds": {
                    "shape": "GetDoctorsRequest_doctorIds"
                }
            }
        },
        "SearchForDoctorsRequest_serviceId": {
            "type": "string"
        },
        "SearchForDoctorsRequest_lastTime": {
            "type": "string"
        },
        "SearchForDoctorsRequest_longitude": {
            "type": "double"
        },
        "SearchForDoctorsRequest_specialtyId": {
            "type": "string"
        },
        "SearchForDoctorsRequest_firstTime": {
            "type": "string"
        },
        "SearchForDoctorsRequest_latitude": {
            "type": "double"
        },
        "SearchForDoctorsRequest": {
            "type": "structure",
            "required": [
                "firstTime",
                "lastTime",
                "latitude",
                "longitude",
                "serviceId",
                "specialtyId"
            ],
            "members": {
                "serviceId": {
                    "shape": "SearchForDoctorsRequest_serviceId"
                },
                "lastTime": {
                    "shape": "SearchForDoctorsRequest_lastTime"
                },
                "longitude": {
                    "shape": "SearchForDoctorsRequest_longitude"
                },
                "specialtyId": {
                    "shape": "SearchForDoctorsRequest_specialtyId"
                },
                "firstTime": {
                    "shape": "SearchForDoctorsRequest_firstTime"
                },
                "latitude": {
                    "shape": "SearchForDoctorsRequest_latitude"
                }
            }
        },
        "GetLoggedInUserResult_userExists": {
            "type": "boolean"
        },
        "GetLoggedInUserResult_user_lastName": {
            "type": "string"
        },
        "GetLoggedInUserResult_user_id": {
            "type": "string"
        },
        "GetLoggedInUserResult_user_stripeCustomerId": {
            "type": "string"
        },
        "GetLoggedInUserResult_user_profilePhotoUrl": {
            "type": "string"
        },
        "GetLoggedInUserResult_user_mobileNumber": {
            "type": "string"
        },
        "GetLoggedInUserResult_user_doctorId": {
            "type": "string"
        },
        "GetLoggedInUserResult_user_firstName": {
            "type": "string"
        },
        "GetLoggedInUserResult_user_email": {
            "type": "string"
        },
        "GetLoggedInUserResult_user": {
            "type": "structure",
            "required": [
                "email",
                "firstName",
                "id",
                "lastName"
            ],
            "members": {
                "lastName": {
                    "shape": "GetLoggedInUserResult_user_lastName"
                },
                "id": {
                    "shape": "GetLoggedInUserResult_user_id"
                },
                "stripeCustomerId": {
                    "shape": "GetLoggedInUserResult_user_stripeCustomerId"
                },
                "profilePhotoUrl": {
                    "shape": "GetLoggedInUserResult_user_profilePhotoUrl"
                },
                "mobileNumber": {
                    "shape": "GetLoggedInUserResult_user_mobileNumber"
                },
                "doctorId": {
                    "shape": "GetLoggedInUserResult_user_doctorId"
                },
                "firstName": {
                    "shape": "GetLoggedInUserResult_user_firstName"
                },
                "email": {
                    "shape": "GetLoggedInUserResult_user_email"
                }
            }
        },
        "GetLoggedInUserResult": {
            "type": "structure",
            "required": [],
            "members": {
                "userExists": {
                    "shape": "GetLoggedInUserResult_userExists"
                },
                "user": {
                    "shape": "GetLoggedInUserResult_user"
                }
            }
        },
        "ClientDoctor_city": {
            "type": "string"
        },
        "ClientDoctor_lastName": {
            "type": "string"
        },
        "ClientDoctor_officeNumber": {
            "type": "string"
        },
        "ClientDoctor_profilePhotoUrl": {
            "type": "string"
        },
        "ClientDoctor_servicesOfferedItem": {
            "type": "string"
        },
        "ClientDoctor_servicesOffered": {
            "type": "list",
            "member": {
                "shape": "ClientDoctor_servicesOfferedItem"
            }
        },
        "ClientDoctor_serviceDetailsListItem_doctorId": {
            "type": "string"
        },
        "ClientDoctor_serviceDetailsListItem_priceDollars": {
            "type": "string"
        },
        "ClientDoctor_serviceDetailsListItem_durationSeconds": {
            "type": "string"
        },
        "ClientDoctor_serviceDetailsListItem_serviceId": {
            "type": "string"
        },
        "ClientDoctor_serviceDetailsListItem": {
            "type": "structure",
            "required": [
                "doctorId",
                "durationSeconds",
                "priceDollars",
                "serviceId"
            ],
            "members": {
                "doctorId": {
                    "shape": "ClientDoctor_serviceDetailsListItem_doctorId"
                },
                "priceDollars": {
                    "shape": "ClientDoctor_serviceDetailsListItem_priceDollars"
                },
                "durationSeconds": {
                    "shape": "ClientDoctor_serviceDetailsListItem_durationSeconds"
                },
                "serviceId": {
                    "shape": "ClientDoctor_serviceDetailsListItem_serviceId"
                }
            }
        },
        "ClientDoctor_serviceDetailsList": {
            "type": "list",
            "member": {
                "shape": "ClientDoctor_serviceDetailsListItem"
            }
        },
        "ClientDoctor_specialtyId": {
            "type": "string"
        },
        "ClientDoctor_streetNumberAndName": {
            "type": "string"
        },
        "ClientDoctor_postalCode": {
            "type": "string"
        },
        "ClientDoctor_administrativeAreaL1": {
            "type": "string"
        },
        "ClientDoctor_coverPhotoUrl": {
            "type": "string"
        },
        "ClientDoctor_payoutInfoIsSet": {
            "type": "boolean"
        },
        "ClientDoctor_firstName": {
            "type": "string"
        },
        "ClientDoctor_longitude": {
            "type": "double"
        },
        "ClientDoctor_suite": {
            "type": "string"
        },
        "ClientDoctor_id": {
            "type": "string"
        },
        "ClientDoctor_latitude": {
            "type": "double"
        },
        "ClientDoctor": {
            "type": "structure",
            "required": [
                "firstName",
                "id",
                "lastName",
                "payoutInfoIsSet",
                "servicesOffered",
                "specialtyId"
            ],
            "members": {
                "city": {
                    "shape": "ClientDoctor_city"
                },
                "lastName": {
                    "shape": "ClientDoctor_lastName"
                },
                "officeNumber": {
                    "shape": "ClientDoctor_officeNumber"
                },
                "profilePhotoUrl": {
                    "shape": "ClientDoctor_profilePhotoUrl"
                },
                "servicesOffered": {
                    "shape": "ClientDoctor_servicesOffered"
                },
                "serviceDetailsList": {
                    "shape": "ClientDoctor_serviceDetailsList"
                },
                "specialtyId": {
                    "shape": "ClientDoctor_specialtyId"
                },
                "streetNumberAndName": {
                    "shape": "ClientDoctor_streetNumberAndName"
                },
                "postalCode": {
                    "shape": "ClientDoctor_postalCode"
                },
                "administrativeAreaL1": {
                    "shape": "ClientDoctor_administrativeAreaL1"
                },
                "coverPhotoUrl": {
                    "shape": "ClientDoctor_coverPhotoUrl"
                },
                "payoutInfoIsSet": {
                    "shape": "ClientDoctor_payoutInfoIsSet"
                },
                "firstName": {
                    "shape": "ClientDoctor_firstName"
                },
                "longitude": {
                    "shape": "ClientDoctor_longitude"
                },
                "suite": {
                    "shape": "ClientDoctor_suite"
                },
                "id": {
                    "shape": "ClientDoctor_id"
                },
                "latitude": {
                    "shape": "ClientDoctor_latitude"
                }
            }
        },
        "StripeObject_jsonString": {
            "type": "string"
        },
        "StripeObject": {
            "type": "structure",
            "required": [],
            "members": {
                "jsonString": {
                    "shape": "StripeObject_jsonString"
                }
            }
        },
        "RegisterUserRequest_lastName": {
            "type": "string"
        },
        "RegisterUserRequest_mobileNumber": {
            "type": "string"
        },
        "RegisterUserRequest_email": {
            "type": "string"
        },
        "RegisterUserRequest_firstName": {
            "type": "string"
        },
        "RegisterUserRequest": {
            "type": "structure",
            "required": [
                "email",
                "firstName",
                "lastName",
                "mobileNumber"
            ],
            "members": {
                "lastName": {
                    "shape": "RegisterUserRequest_lastName"
                },
                "mobileNumber": {
                    "shape": "RegisterUserRequest_mobileNumber"
                },
                "email": {
                    "shape": "RegisterUserRequest_email"
                },
                "firstName": {
                    "shape": "RegisterUserRequest_firstName"
                }
            }
        },
        "UrlForFileResult_url": {
            "type": "string"
        },
        "UrlForFileResult": {
            "type": "structure",
            "required": [],
            "members": {
                "url": {
                    "shape": "UrlForFileResult_url"
                }
            }
        },
        "SearchForDoctorsResult_doctorsItem_city": {
            "type": "string"
        },
        "SearchForDoctorsResult_doctorsItem_lastName": {
            "type": "string"
        },
        "SearchForDoctorsResult_doctorsItem_officeNumber": {
            "type": "string"
        },
        "SearchForDoctorsResult_doctorsItem_profilePhotoUrl": {
            "type": "string"
        },
        "SearchForDoctorsResult_doctorsItem_servicesOfferedItem": {
            "type": "string"
        },
        "SearchForDoctorsResult_doctorsItem_servicesOffered": {
            "type": "list",
            "member": {
                "shape": "SearchForDoctorsResult_doctorsItem_servicesOfferedItem"
            }
        },
        "SearchForDoctorsResult_doctorsItem_serviceDetailsListItem_doctorId": {
            "type": "string"
        },
        "SearchForDoctorsResult_doctorsItem_serviceDetailsListItem_priceDollars": {
            "type": "string"
        },
        "SearchForDoctorsResult_doctorsItem_serviceDetailsListItem_durationSeconds": {
            "type": "string"
        },
        "SearchForDoctorsResult_doctorsItem_serviceDetailsListItem_serviceId": {
            "type": "string"
        },
        "SearchForDoctorsResult_doctorsItem_serviceDetailsListItem": {
            "type": "structure",
            "required": [
                "doctorId",
                "durationSeconds",
                "priceDollars",
                "serviceId"
            ],
            "members": {
                "doctorId": {
                    "shape": "SearchForDoctorsResult_doctorsItem_serviceDetailsListItem_doctorId"
                },
                "priceDollars": {
                    "shape": "SearchForDoctorsResult_doctorsItem_serviceDetailsListItem_priceDollars"
                },
                "durationSeconds": {
                    "shape": "SearchForDoctorsResult_doctorsItem_serviceDetailsListItem_durationSeconds"
                },
                "serviceId": {
                    "shape": "SearchForDoctorsResult_doctorsItem_serviceDetailsListItem_serviceId"
                }
            }
        },
        "SearchForDoctorsResult_doctorsItem_serviceDetailsList": {
            "type": "list",
            "member": {
                "shape": "SearchForDoctorsResult_doctorsItem_serviceDetailsListItem"
            }
        },
        "SearchForDoctorsResult_doctorsItem_specialtyId": {
            "type": "string"
        },
        "SearchForDoctorsResult_doctorsItem_streetNumberAndName": {
            "type": "string"
        },
        "SearchForDoctorsResult_doctorsItem_postalCode": {
            "type": "string"
        },
        "SearchForDoctorsResult_doctorsItem_administrativeAreaL1": {
            "type": "string"
        },
        "SearchForDoctorsResult_doctorsItem_coverPhotoUrl": {
            "type": "string"
        },
        "SearchForDoctorsResult_doctorsItem_payoutInfoIsSet": {
            "type": "boolean"
        },
        "SearchForDoctorsResult_doctorsItem_firstName": {
            "type": "string"
        },
        "SearchForDoctorsResult_doctorsItem_longitude": {
            "type": "double"
        },
        "SearchForDoctorsResult_doctorsItem_suite": {
            "type": "string"
        },
        "SearchForDoctorsResult_doctorsItem_id": {
            "type": "string"
        },
        "SearchForDoctorsResult_doctorsItem_latitude": {
            "type": "double"
        },
        "SearchForDoctorsResult_doctorsItem": {
            "type": "structure",
            "required": [
                "firstName",
                "id",
                "lastName",
                "payoutInfoIsSet",
                "servicesOffered",
                "specialtyId"
            ],
            "members": {
                "city": {
                    "shape": "SearchForDoctorsResult_doctorsItem_city"
                },
                "lastName": {
                    "shape": "SearchForDoctorsResult_doctorsItem_lastName"
                },
                "officeNumber": {
                    "shape": "SearchForDoctorsResult_doctorsItem_officeNumber"
                },
                "profilePhotoUrl": {
                    "shape": "SearchForDoctorsResult_doctorsItem_profilePhotoUrl"
                },
                "servicesOffered": {
                    "shape": "SearchForDoctorsResult_doctorsItem_servicesOffered"
                },
                "serviceDetailsList": {
                    "shape": "SearchForDoctorsResult_doctorsItem_serviceDetailsList"
                },
                "specialtyId": {
                    "shape": "SearchForDoctorsResult_doctorsItem_specialtyId"
                },
                "streetNumberAndName": {
                    "shape": "SearchForDoctorsResult_doctorsItem_streetNumberAndName"
                },
                "postalCode": {
                    "shape": "SearchForDoctorsResult_doctorsItem_postalCode"
                },
                "administrativeAreaL1": {
                    "shape": "SearchForDoctorsResult_doctorsItem_administrativeAreaL1"
                },
                "coverPhotoUrl": {
                    "shape": "SearchForDoctorsResult_doctorsItem_coverPhotoUrl"
                },
                "payoutInfoIsSet": {
                    "shape": "SearchForDoctorsResult_doctorsItem_payoutInfoIsSet"
                },
                "firstName": {
                    "shape": "SearchForDoctorsResult_doctorsItem_firstName"
                },
                "longitude": {
                    "shape": "SearchForDoctorsResult_doctorsItem_longitude"
                },
                "suite": {
                    "shape": "SearchForDoctorsResult_doctorsItem_suite"
                },
                "id": {
                    "shape": "SearchForDoctorsResult_doctorsItem_id"
                },
                "latitude": {
                    "shape": "SearchForDoctorsResult_doctorsItem_latitude"
                }
            }
        },
        "SearchForDoctorsResult_doctors": {
            "type": "list",
            "member": {
                "shape": "SearchForDoctorsResult_doctorsItem"
            }
        },
        "SearchForDoctorsResult": {
            "type": "structure",
            "required": [],
            "members": {
                "doctors": {
                    "shape": "SearchForDoctorsResult_doctors"
                }
            }
        },
        "GetAppointmentsWithUserRequest_getDoctors": {
            "type": "boolean"
        },
        "GetAppointmentsWithUserRequest_userId": {
            "type": "string"
        },
        "GetAppointmentsWithUserRequest_getPatients": {
            "type": "boolean"
        },
        "GetAppointmentsWithUserRequest": {
            "type": "structure",
            "required": [
                "getDoctors",
                "getPatients",
                "userId"
            ],
            "members": {
                "getDoctors": {
                    "shape": "GetAppointmentsWithUserRequest_getDoctors"
                },
                "userId": {
                    "shape": "GetAppointmentsWithUserRequest_userId"
                },
                "getPatients": {
                    "shape": "GetAppointmentsWithUserRequest_getPatients"
                }
            }
        },
        "QueryDoctorScheduleRequest_doctorId": {
            "type": "string"
        },
        "QueryDoctorScheduleRequest_lastTime": {
            "type": "string"
        },
        "QueryDoctorScheduleRequest_firstTime": {
            "type": "string"
        },
        "QueryDoctorScheduleRequest": {
            "type": "structure",
            "required": [],
            "members": {
                "doctorId": {
                    "shape": "QueryDoctorScheduleRequest_doctorId"
                },
                "lastTime": {
                    "shape": "QueryDoctorScheduleRequest_lastTime"
                },
                "firstTime": {
                    "shape": "QueryDoctorScheduleRequest_firstTime"
                }
            }
        },
        "CancelAppointmentRequest_appointmentId": {
            "type": "string"
        },
        "CancelAppointmentRequest_lateCancellation": {
            "type": "boolean"
        },
        "CancelAppointmentRequest": {
            "type": "structure",
            "required": [
                "appointmentId",
                "lateCancellation"
            ],
            "members": {
                "appointmentId": {
                    "shape": "CancelAppointmentRequest_appointmentId"
                },
                "lateCancellation": {
                    "shape": "CancelAppointmentRequest_lateCancellation"
                }
            }
        },
        "GetAppointmentBillRequest_startTime": {
            "type": "string"
        },
        "GetAppointmentBillRequest_doctorId": {
            "type": "string"
        },
        "GetAppointmentBillRequest_serviceId": {
            "type": "string"
        },
        "GetAppointmentBillRequest": {
            "type": "structure",
            "required": [
                "doctorId",
                "serviceId",
                "startTime"
            ],
            "members": {
                "startTime": {
                    "shape": "GetAppointmentBillRequest_startTime"
                },
                "doctorId": {
                    "shape": "GetAppointmentBillRequest_doctorId"
                },
                "serviceId": {
                    "shape": "GetAppointmentBillRequest_serviceId"
                }
            }
        },
        "Empty": {
            "type": "structure",
            "required": [],
            "members": {}
        },
        "VitalServicesRequest_getDoctors": {
            "type": "boolean"
        },
        "VitalServicesRequest_officeNumber": {
            "type": "string"
        },
        "VitalServicesRequest_employerIdentificationNumber": {
            "type": "string"
        },
        "VitalServicesRequest_patientId": {
            "type": "string"
        },
        "VitalServicesRequest_lateCancellation": {
            "type": "boolean"
        },
        "VitalServicesRequest_doctorIdsItem": {
            "type": "string"
        },
        "VitalServicesRequest_doctorIds": {
            "type": "list",
            "member": {
                "shape": "VitalServicesRequest_doctorIdsItem"
            }
        },
        "VitalServicesRequest_birthdateMonth": {
            "type": "string"
        },
        "VitalServicesRequest_serviceIdsItem": {
            "type": "string"
        },
        "VitalServicesRequest_serviceIds": {
            "type": "list",
            "member": {
                "shape": "VitalServicesRequest_serviceIdsItem"
            }
        },
        "VitalServicesRequest_appointmentIdsItem": {
            "type": "string"
        },
        "VitalServicesRequest_appointmentIds": {
            "type": "list",
            "member": {
                "shape": "VitalServicesRequest_appointmentIdsItem"
            }
        },
        "VitalServicesRequest_durationMinutes": {
            "type": "string"
        },
        "VitalServicesRequest_city": {
            "type": "string"
        },
        "VitalServicesRequest_billVersion": {
            "type": "string"
        },
        "VitalServicesRequest_lastTime": {
            "type": "string"
        },
        "VitalServicesRequest_birthdateDay": {
            "type": "string"
        },
        "VitalServicesRequest_string1": {
            "type": "string"
        },
        "VitalServicesRequest_firstTime": {
            "type": "string"
        },
        "VitalServicesRequest_latitude": {
            "type": "double"
        },
        "VitalServicesRequest_mobileNumber": {
            "type": "string"
        },
        "VitalServicesRequest_file": {
            "type": "string"
        },
        "VitalServicesRequest_sourceId": {
            "type": "string"
        },
        "VitalServicesRequest_string3": {
            "type": "string"
        },
        "VitalServicesRequest_operation": {
            "type": "string"
        },
        "VitalServicesRequest_specialtyId": {
            "type": "string"
        },
        "VitalServicesRequest_priceDollars": {
            "type": "string"
        },
        "VitalServicesRequest_availableTimeSlotsItem": {
            "type": "string"
        },
        "VitalServicesRequest_availableTimeSlots": {
            "type": "list",
            "member": {
                "shape": "VitalServicesRequest_availableTimeSlotsItem"
            }
        },
        "VitalServicesRequest_patientIdsItem": {
            "type": "string"
        },
        "VitalServicesRequest_patientIds": {
            "type": "list",
            "member": {
                "shape": "VitalServicesRequest_patientIdsItem"
            }
        },
        "VitalServicesRequest_string2": {
            "type": "string"
        },
        "VitalServicesRequest_pictureUrl": {
            "type": "string"
        },
        "VitalServicesRequest_postalCode": {
            "type": "string"
        },
        "VitalServicesRequest_longitude": {
            "type": "double"
        },
        "VitalServicesRequest_email": {
            "type": "string"
        },
        "VitalServicesRequest_firstName": {
            "type": "string"
        },
        "VitalServicesRequest_appointmentId": {
            "type": "string"
        },
        "VitalServicesRequest_startTime": {
            "type": "string"
        },
        "VitalServicesRequest_businessName": {
            "type": "string"
        },
        "VitalServicesRequest_lastName": {
            "type": "string"
        },
        "VitalServicesRequest_httpMethod": {
            "type": "string"
        },
        "VitalServicesRequest_streetNumberAndName": {
            "type": "string"
        },
        "VitalServicesRequest_doctorId": {
            "type": "string"
        },
        "VitalServicesRequest_cardToken": {
            "type": "string"
        },
        "VitalServicesRequest_bankAccountToken": {
            "type": "string"
        },
        "VitalServicesRequest_serviceId": {
            "type": "string"
        },
        "VitalServicesRequest_unavailableTimeSlotsItem": {
            "type": "string"
        },
        "VitalServicesRequest_unavailableTimeSlots": {
            "type": "list",
            "member": {
                "shape": "VitalServicesRequest_unavailableTimeSlotsItem"
            }
        },
        "VitalServicesRequest_suite": {
            "type": "string"
        },
        "VitalServicesRequest_ssnLast4": {
            "type": "string"
        },
        "VitalServicesRequest_birthdateYear": {
            "type": "string"
        },
        "VitalServicesRequest_string4": {
            "type": "string"
        },
        "VitalServicesRequest_getPatients": {
            "type": "boolean"
        },
        "VitalServicesRequest_state": {
            "type": "string"
        },
        "VitalServicesRequest": {
            "type": "structure",
            "required": [],
            "members": {
                "getDoctors": {
                    "shape": "VitalServicesRequest_getDoctors"
                },
                "officeNumber": {
                    "shape": "VitalServicesRequest_officeNumber"
                },
                "employerIdentificationNumber": {
                    "shape": "VitalServicesRequest_employerIdentificationNumber"
                },
                "patientId": {
                    "shape": "VitalServicesRequest_patientId"
                },
                "lateCancellation": {
                    "shape": "VitalServicesRequest_lateCancellation"
                },
                "doctorIds": {
                    "shape": "VitalServicesRequest_doctorIds"
                },
                "birthdateMonth": {
                    "shape": "VitalServicesRequest_birthdateMonth"
                },
                "serviceIds": {
                    "shape": "VitalServicesRequest_serviceIds"
                },
                "appointmentIds": {
                    "shape": "VitalServicesRequest_appointmentIds"
                },
                "durationMinutes": {
                    "shape": "VitalServicesRequest_durationMinutes"
                },
                "city": {
                    "shape": "VitalServicesRequest_city"
                },
                "billVersion": {
                    "shape": "VitalServicesRequest_billVersion"
                },
                "lastTime": {
                    "shape": "VitalServicesRequest_lastTime"
                },
                "birthdateDay": {
                    "shape": "VitalServicesRequest_birthdateDay"
                },
                "string1": {
                    "shape": "VitalServicesRequest_string1"
                },
                "firstTime": {
                    "shape": "VitalServicesRequest_firstTime"
                },
                "latitude": {
                    "shape": "VitalServicesRequest_latitude"
                },
                "mobileNumber": {
                    "shape": "VitalServicesRequest_mobileNumber"
                },
                "file": {
                    "shape": "VitalServicesRequest_file"
                },
                "sourceId": {
                    "shape": "VitalServicesRequest_sourceId"
                },
                "string3": {
                    "shape": "VitalServicesRequest_string3"
                },
                "operation": {
                    "shape": "VitalServicesRequest_operation"
                },
                "specialtyId": {
                    "shape": "VitalServicesRequest_specialtyId"
                },
                "priceDollars": {
                    "shape": "VitalServicesRequest_priceDollars"
                },
                "availableTimeSlots": {
                    "shape": "VitalServicesRequest_availableTimeSlots"
                },
                "patientIds": {
                    "shape": "VitalServicesRequest_patientIds"
                },
                "string2": {
                    "shape": "VitalServicesRequest_string2"
                },
                "pictureUrl": {
                    "shape": "VitalServicesRequest_pictureUrl"
                },
                "postalCode": {
                    "shape": "VitalServicesRequest_postalCode"
                },
                "longitude": {
                    "shape": "VitalServicesRequest_longitude"
                },
                "email": {
                    "shape": "VitalServicesRequest_email"
                },
                "firstName": {
                    "shape": "VitalServicesRequest_firstName"
                },
                "appointmentId": {
                    "shape": "VitalServicesRequest_appointmentId"
                },
                "startTime": {
                    "shape": "VitalServicesRequest_startTime"
                },
                "businessName": {
                    "shape": "VitalServicesRequest_businessName"
                },
                "lastName": {
                    "shape": "VitalServicesRequest_lastName"
                },
                "httpMethod": {
                    "shape": "VitalServicesRequest_httpMethod"
                },
                "streetNumberAndName": {
                    "shape": "VitalServicesRequest_streetNumberAndName"
                },
                "doctorId": {
                    "shape": "VitalServicesRequest_doctorId"
                },
                "cardToken": {
                    "shape": "VitalServicesRequest_cardToken"
                },
                "bankAccountToken": {
                    "shape": "VitalServicesRequest_bankAccountToken"
                },
                "serviceId": {
                    "shape": "VitalServicesRequest_serviceId"
                },
                "unavailableTimeSlots": {
                    "shape": "VitalServicesRequest_unavailableTimeSlots"
                },
                "suite": {
                    "shape": "VitalServicesRequest_suite"
                },
                "ssnLast4": {
                    "shape": "VitalServicesRequest_ssnLast4"
                },
                "birthdateYear": {
                    "shape": "VitalServicesRequest_birthdateYear"
                },
                "string4": {
                    "shape": "VitalServicesRequest_string4"
                },
                "getPatients": {
                    "shape": "VitalServicesRequest_getPatients"
                },
                "state": {
                    "shape": "VitalServicesRequest_state"
                }
            }
        },
        "ClientDoctorScheduleTimeSlot_timeSlot": {
            "type": "string"
        },
        "ClientDoctorScheduleTimeSlot_appointmentId": {
            "type": "string"
        },
        "ClientDoctorScheduleTimeSlot": {
            "type": "structure",
            "required": [
                "timeSlot"
            ],
            "members": {
                "timeSlot": {
                    "shape": "ClientDoctorScheduleTimeSlot_timeSlot"
                },
                "appointmentId": {
                    "shape": "ClientDoctorScheduleTimeSlot_appointmentId"
                }
            }
        },
        "GetAppointmentPaymentMethodRequest_appointmentId": {
            "type": "string"
        },
        "GetAppointmentPaymentMethodRequest": {
            "type": "structure",
            "required": [],
            "members": {
                "appointmentId": {
                    "shape": "GetAppointmentPaymentMethodRequest_appointmentId"
                }
            }
        },
        "GetDoctorsResult_doctorsItem_city": {
            "type": "string"
        },
        "GetDoctorsResult_doctorsItem_lastName": {
            "type": "string"
        },
        "GetDoctorsResult_doctorsItem_officeNumber": {
            "type": "string"
        },
        "GetDoctorsResult_doctorsItem_profilePhotoUrl": {
            "type": "string"
        },
        "GetDoctorsResult_doctorsItem_servicesOfferedItem": {
            "type": "string"
        },
        "GetDoctorsResult_doctorsItem_servicesOffered": {
            "type": "list",
            "member": {
                "shape": "GetDoctorsResult_doctorsItem_servicesOfferedItem"
            }
        },
        "GetDoctorsResult_doctorsItem_serviceDetailsListItem_doctorId": {
            "type": "string"
        },
        "GetDoctorsResult_doctorsItem_serviceDetailsListItem_priceDollars": {
            "type": "string"
        },
        "GetDoctorsResult_doctorsItem_serviceDetailsListItem_durationSeconds": {
            "type": "string"
        },
        "GetDoctorsResult_doctorsItem_serviceDetailsListItem_serviceId": {
            "type": "string"
        },
        "GetDoctorsResult_doctorsItem_serviceDetailsListItem": {
            "type": "structure",
            "required": [
                "doctorId",
                "durationSeconds",
                "priceDollars",
                "serviceId"
            ],
            "members": {
                "doctorId": {
                    "shape": "GetDoctorsResult_doctorsItem_serviceDetailsListItem_doctorId"
                },
                "priceDollars": {
                    "shape": "GetDoctorsResult_doctorsItem_serviceDetailsListItem_priceDollars"
                },
                "durationSeconds": {
                    "shape": "GetDoctorsResult_doctorsItem_serviceDetailsListItem_durationSeconds"
                },
                "serviceId": {
                    "shape": "GetDoctorsResult_doctorsItem_serviceDetailsListItem_serviceId"
                }
            }
        },
        "GetDoctorsResult_doctorsItem_serviceDetailsList": {
            "type": "list",
            "member": {
                "shape": "GetDoctorsResult_doctorsItem_serviceDetailsListItem"
            }
        },
        "GetDoctorsResult_doctorsItem_specialtyId": {
            "type": "string"
        },
        "GetDoctorsResult_doctorsItem_streetNumberAndName": {
            "type": "string"
        },
        "GetDoctorsResult_doctorsItem_postalCode": {
            "type": "string"
        },
        "GetDoctorsResult_doctorsItem_administrativeAreaL1": {
            "type": "string"
        },
        "GetDoctorsResult_doctorsItem_coverPhotoUrl": {
            "type": "string"
        },
        "GetDoctorsResult_doctorsItem_payoutInfoIsSet": {
            "type": "boolean"
        },
        "GetDoctorsResult_doctorsItem_firstName": {
            "type": "string"
        },
        "GetDoctorsResult_doctorsItem_longitude": {
            "type": "double"
        },
        "GetDoctorsResult_doctorsItem_suite": {
            "type": "string"
        },
        "GetDoctorsResult_doctorsItem_id": {
            "type": "string"
        },
        "GetDoctorsResult_doctorsItem_latitude": {
            "type": "double"
        },
        "GetDoctorsResult_doctorsItem": {
            "type": "structure",
            "required": [
                "firstName",
                "id",
                "lastName",
                "payoutInfoIsSet",
                "servicesOffered",
                "specialtyId"
            ],
            "members": {
                "city": {
                    "shape": "GetDoctorsResult_doctorsItem_city"
                },
                "lastName": {
                    "shape": "GetDoctorsResult_doctorsItem_lastName"
                },
                "officeNumber": {
                    "shape": "GetDoctorsResult_doctorsItem_officeNumber"
                },
                "profilePhotoUrl": {
                    "shape": "GetDoctorsResult_doctorsItem_profilePhotoUrl"
                },
                "servicesOffered": {
                    "shape": "GetDoctorsResult_doctorsItem_servicesOffered"
                },
                "serviceDetailsList": {
                    "shape": "GetDoctorsResult_doctorsItem_serviceDetailsList"
                },
                "specialtyId": {
                    "shape": "GetDoctorsResult_doctorsItem_specialtyId"
                },
                "streetNumberAndName": {
                    "shape": "GetDoctorsResult_doctorsItem_streetNumberAndName"
                },
                "postalCode": {
                    "shape": "GetDoctorsResult_doctorsItem_postalCode"
                },
                "administrativeAreaL1": {
                    "shape": "GetDoctorsResult_doctorsItem_administrativeAreaL1"
                },
                "coverPhotoUrl": {
                    "shape": "GetDoctorsResult_doctorsItem_coverPhotoUrl"
                },
                "payoutInfoIsSet": {
                    "shape": "GetDoctorsResult_doctorsItem_payoutInfoIsSet"
                },
                "firstName": {
                    "shape": "GetDoctorsResult_doctorsItem_firstName"
                },
                "longitude": {
                    "shape": "GetDoctorsResult_doctorsItem_longitude"
                },
                "suite": {
                    "shape": "GetDoctorsResult_doctorsItem_suite"
                },
                "id": {
                    "shape": "GetDoctorsResult_doctorsItem_id"
                },
                "latitude": {
                    "shape": "GetDoctorsResult_doctorsItem_latitude"
                }
            }
        },
        "GetDoctorsResult_doctors": {
            "type": "list",
            "member": {
                "shape": "GetDoctorsResult_doctorsItem"
            }
        },
        "GetDoctorsResult": {
            "type": "structure",
            "required": [],
            "members": {
                "doctors": {
                    "shape": "GetDoctorsResult_doctors"
                }
            }
        },
        "ClientDoctorServiceDetails_doctorId": {
            "type": "string"
        },
        "ClientDoctorServiceDetails_priceDollars": {
            "type": "string"
        },
        "ClientDoctorServiceDetails_durationSeconds": {
            "type": "string"
        },
        "ClientDoctorServiceDetails_serviceId": {
            "type": "string"
        },
        "ClientDoctorServiceDetails": {
            "type": "structure",
            "required": [
                "doctorId",
                "durationSeconds",
                "priceDollars",
                "serviceId"
            ],
            "members": {
                "doctorId": {
                    "shape": "ClientDoctorServiceDetails_doctorId"
                },
                "priceDollars": {
                    "shape": "ClientDoctorServiceDetails_priceDollars"
                },
                "durationSeconds": {
                    "shape": "ClientDoctorServiceDetails_durationSeconds"
                },
                "serviceId": {
                    "shape": "ClientDoctorServiceDetails_serviceId"
                }
            }
        },
        "ClientPatient_profilePhotoUrl": {
            "type": "string"
        },
        "ClientPatient_lastName": {
            "type": "string"
        },
        "ClientPatient_mobileNumber": {
            "type": "string"
        },
        "ClientPatient_firstName": {
            "type": "string"
        },
        "ClientPatient_id": {
            "type": "string"
        },
        "ClientPatient": {
            "type": "structure",
            "required": [
                "firstName",
                "id",
                "lastName",
                "mobileNumber"
            ],
            "members": {
                "profilePhotoUrl": {
                    "shape": "ClientPatient_profilePhotoUrl"
                },
                "lastName": {
                    "shape": "ClientPatient_lastName"
                },
                "mobileNumber": {
                    "shape": "ClientPatient_mobileNumber"
                },
                "firstName": {
                    "shape": "ClientPatient_firstName"
                },
                "id": {
                    "shape": "ClientPatient_id"
                }
            }
        },
        "ScheduleAppointmentRequest_startTime": {
            "type": "string"
        },
        "ScheduleAppointmentRequest_doctorId": {
            "type": "string"
        },
        "ScheduleAppointmentRequest_billVersion": {
            "type": "string"
        },
        "ScheduleAppointmentRequest_serviceId": {
            "type": "string"
        },
        "ScheduleAppointmentRequest": {
            "type": "structure",
            "required": [
                "billVersion",
                "doctorId",
                "serviceId",
                "startTime"
            ],
            "members": {
                "startTime": {
                    "shape": "ScheduleAppointmentRequest_startTime"
                },
                "doctorId": {
                    "shape": "ScheduleAppointmentRequest_doctorId"
                },
                "billVersion": {
                    "shape": "ScheduleAppointmentRequest_billVersion"
                },
                "serviceId": {
                    "shape": "ScheduleAppointmentRequest_serviceId"
                }
            }
        },
        "CancelAppointmentResult_errorCode": {
            "type": "string"
        },
        "CancelAppointmentResult_appointment_startTime": {
            "type": "string"
        },
        "CancelAppointmentResult_appointment_cancellationDate": {
            "type": "string"
        },
        "CancelAppointmentResult_appointment_dateBooked": {
            "type": "string"
        },
        "CancelAppointmentResult_appointment_basePrice": {
            "type": "string"
        },
        "CancelAppointmentResult_appointment_patientId": {
            "type": "string"
        },
        "CancelAppointmentResult_appointment_doctorEarnings": {
            "type": "string"
        },
        "CancelAppointmentResult_appointment_doctorServiceFee": {
            "type": "string"
        },
        "CancelAppointmentResult_appointment_appointmentState": {
            "type": "string"
        },
        "CancelAppointmentResult_appointment_amountRefunded": {
            "type": "string"
        },
        "CancelAppointmentResult_appointment_doctorId": {
            "type": "string"
        },
        "CancelAppointmentResult_appointment_patientServiceFee": {
            "type": "string"
        },
        "CancelAppointmentResult_appointment_serviceId": {
            "type": "string"
        },
        "CancelAppointmentResult_appointment_totalPrice": {
            "type": "string"
        },
        "CancelAppointmentResult_appointment_reimbursementDate": {
            "type": "string"
        },
        "CancelAppointmentResult_appointment_durationSeconds": {
            "type": "string"
        },
        "CancelAppointmentResult_appointment_chargeId": {
            "type": "string"
        },
        "CancelAppointmentResult_appointment_id": {
            "type": "string"
        },
        "CancelAppointmentResult_appointment": {
            "type": "structure",
            "required": [
                "appointmentState",
                "basePrice",
                "chargeId",
                "dateBooked",
                "doctorEarnings",
                "doctorId",
                "doctorServiceFee",
                "durationSeconds",
                "id",
                "patientId",
                "patientServiceFee",
                "serviceId",
                "startTime",
                "totalPrice"
            ],
            "members": {
                "startTime": {
                    "shape": "CancelAppointmentResult_appointment_startTime"
                },
                "cancellationDate": {
                    "shape": "CancelAppointmentResult_appointment_cancellationDate"
                },
                "dateBooked": {
                    "shape": "CancelAppointmentResult_appointment_dateBooked"
                },
                "basePrice": {
                    "shape": "CancelAppointmentResult_appointment_basePrice"
                },
                "patientId": {
                    "shape": "CancelAppointmentResult_appointment_patientId"
                },
                "doctorEarnings": {
                    "shape": "CancelAppointmentResult_appointment_doctorEarnings"
                },
                "doctorServiceFee": {
                    "shape": "CancelAppointmentResult_appointment_doctorServiceFee"
                },
                "appointmentState": {
                    "shape": "CancelAppointmentResult_appointment_appointmentState"
                },
                "amountRefunded": {
                    "shape": "CancelAppointmentResult_appointment_amountRefunded"
                },
                "doctorId": {
                    "shape": "CancelAppointmentResult_appointment_doctorId"
                },
                "patientServiceFee": {
                    "shape": "CancelAppointmentResult_appointment_patientServiceFee"
                },
                "serviceId": {
                    "shape": "CancelAppointmentResult_appointment_serviceId"
                },
                "totalPrice": {
                    "shape": "CancelAppointmentResult_appointment_totalPrice"
                },
                "reimbursementDate": {
                    "shape": "CancelAppointmentResult_appointment_reimbursementDate"
                },
                "durationSeconds": {
                    "shape": "CancelAppointmentResult_appointment_durationSeconds"
                },
                "chargeId": {
                    "shape": "CancelAppointmentResult_appointment_chargeId"
                },
                "id": {
                    "shape": "CancelAppointmentResult_appointment_id"
                }
            }
        },
        "CancelAppointmentResult": {
            "type": "structure",
            "required": [],
            "members": {
                "errorCode": {
                    "shape": "CancelAppointmentResult_errorCode"
                },
                "appointment": {
                    "shape": "CancelAppointmentResult_appointment"
                }
            }
        },
        "GetStripeCustomerRequest_userId": {
            "type": "string"
        },
        "GetStripeCustomerRequest": {
            "type": "structure",
            "required": [
                "userId"
            ],
            "members": {
                "userId": {
                    "shape": "GetStripeCustomerRequest_userId"
                }
            }
        },
        "ClientUser_lastName": {
            "type": "string"
        },
        "ClientUser_id": {
            "type": "string"
        },
        "ClientUser_stripeCustomerId": {
            "type": "string"
        },
        "ClientUser_profilePhotoUrl": {
            "type": "string"
        },
        "ClientUser_mobileNumber": {
            "type": "string"
        },
        "ClientUser_doctorId": {
            "type": "string"
        },
        "ClientUser_firstName": {
            "type": "string"
        },
        "ClientUser_email": {
            "type": "string"
        },
        "ClientUser": {
            "type": "structure",
            "required": [
                "email",
                "firstName",
                "id",
                "lastName"
            ],
            "members": {
                "lastName": {
                    "shape": "ClientUser_lastName"
                },
                "id": {
                    "shape": "ClientUser_id"
                },
                "stripeCustomerId": {
                    "shape": "ClientUser_stripeCustomerId"
                },
                "profilePhotoUrl": {
                    "shape": "ClientUser_profilePhotoUrl"
                },
                "mobileNumber": {
                    "shape": "ClientUser_mobileNumber"
                },
                "doctorId": {
                    "shape": "ClientUser_doctorId"
                },
                "firstName": {
                    "shape": "ClientUser_firstName"
                },
                "email": {
                    "shape": "ClientUser_email"
                }
            }
        },
        "QueryDoctorScheduleResult_timeSlotsItem_timeSlot": {
            "type": "string"
        },
        "QueryDoctorScheduleResult_timeSlotsItem_appointmentId": {
            "type": "string"
        },
        "QueryDoctorScheduleResult_timeSlotsItem": {
            "type": "structure",
            "required": [
                "timeSlot"
            ],
            "members": {
                "timeSlot": {
                    "shape": "QueryDoctorScheduleResult_timeSlotsItem_timeSlot"
                },
                "appointmentId": {
                    "shape": "QueryDoctorScheduleResult_timeSlotsItem_appointmentId"
                }
            }
        },
        "QueryDoctorScheduleResult_timeSlots": {
            "type": "list",
            "member": {
                "shape": "QueryDoctorScheduleResult_timeSlotsItem"
            }
        },
        "QueryDoctorScheduleResult": {
            "type": "structure",
            "required": [],
            "members": {
                "timeSlots": {
                    "shape": "QueryDoctorScheduleResult_timeSlots"
                }
            }
        },
        "ScheduleAppointmentResult_succeeded": {
            "type": "boolean"
        },
        "ScheduleAppointmentResult": {
            "type": "structure",
            "required": [],
            "members": {
                "succeeded": {
                    "shape": "ScheduleAppointmentResult_succeeded"
                }
            }
        },
        "ClientAppointment_startTime": {
            "type": "string"
        },
        "ClientAppointment_cancellationDate": {
            "type": "string"
        },
        "ClientAppointment_dateBooked": {
            "type": "string"
        },
        "ClientAppointment_basePrice": {
            "type": "string"
        },
        "ClientAppointment_patientId": {
            "type": "string"
        },
        "ClientAppointment_doctorEarnings": {
            "type": "string"
        },
        "ClientAppointment_doctorServiceFee": {
            "type": "string"
        },
        "ClientAppointment_appointmentState": {
            "type": "string"
        },
        "ClientAppointment_amountRefunded": {
            "type": "string"
        },
        "ClientAppointment_doctorId": {
            "type": "string"
        },
        "ClientAppointment_patientServiceFee": {
            "type": "string"
        },
        "ClientAppointment_serviceId": {
            "type": "string"
        },
        "ClientAppointment_totalPrice": {
            "type": "string"
        },
        "ClientAppointment_reimbursementDate": {
            "type": "string"
        },
        "ClientAppointment_durationSeconds": {
            "type": "string"
        },
        "ClientAppointment_chargeId": {
            "type": "string"
        },
        "ClientAppointment_id": {
            "type": "string"
        },
        "ClientAppointment": {
            "type": "structure",
            "required": [
                "appointmentState",
                "basePrice",
                "chargeId",
                "dateBooked",
                "doctorEarnings",
                "doctorId",
                "doctorServiceFee",
                "durationSeconds",
                "id",
                "patientId",
                "patientServiceFee",
                "serviceId",
                "startTime",
                "totalPrice"
            ],
            "members": {
                "startTime": {
                    "shape": "ClientAppointment_startTime"
                },
                "cancellationDate": {
                    "shape": "ClientAppointment_cancellationDate"
                },
                "dateBooked": {
                    "shape": "ClientAppointment_dateBooked"
                },
                "basePrice": {
                    "shape": "ClientAppointment_basePrice"
                },
                "patientId": {
                    "shape": "ClientAppointment_patientId"
                },
                "doctorEarnings": {
                    "shape": "ClientAppointment_doctorEarnings"
                },
                "doctorServiceFee": {
                    "shape": "ClientAppointment_doctorServiceFee"
                },
                "appointmentState": {
                    "shape": "ClientAppointment_appointmentState"
                },
                "amountRefunded": {
                    "shape": "ClientAppointment_amountRefunded"
                },
                "doctorId": {
                    "shape": "ClientAppointment_doctorId"
                },
                "patientServiceFee": {
                    "shape": "ClientAppointment_patientServiceFee"
                },
                "serviceId": {
                    "shape": "ClientAppointment_serviceId"
                },
                "totalPrice": {
                    "shape": "ClientAppointment_totalPrice"
                },
                "reimbursementDate": {
                    "shape": "ClientAppointment_reimbursementDate"
                },
                "durationSeconds": {
                    "shape": "ClientAppointment_durationSeconds"
                },
                "chargeId": {
                    "shape": "ClientAppointment_chargeId"
                },
                "id": {
                    "shape": "ClientAppointment_id"
                }
            }
        },
        "UpdateUserRequest_mobileNumber": {
            "type": "string"
        },
        "UpdateUserRequest_email": {
            "type": "string"
        },
        "UpdateUserRequest": {
            "type": "structure",
            "required": [],
            "members": {
                "mobileNumber": {
                    "shape": "UpdateUserRequest_mobileNumber"
                },
                "email": {
                    "shape": "UpdateUserRequest_email"
                }
            }
        },
        "GetAppointmentsResult_appointmentsItem_startTime": {
            "type": "string"
        },
        "GetAppointmentsResult_appointmentsItem_cancellationDate": {
            "type": "string"
        },
        "GetAppointmentsResult_appointmentsItem_dateBooked": {
            "type": "string"
        },
        "GetAppointmentsResult_appointmentsItem_basePrice": {
            "type": "string"
        },
        "GetAppointmentsResult_appointmentsItem_patientId": {
            "type": "string"
        },
        "GetAppointmentsResult_appointmentsItem_doctorEarnings": {
            "type": "string"
        },
        "GetAppointmentsResult_appointmentsItem_doctorServiceFee": {
            "type": "string"
        },
        "GetAppointmentsResult_appointmentsItem_appointmentState": {
            "type": "string"
        },
        "GetAppointmentsResult_appointmentsItem_amountRefunded": {
            "type": "string"
        },
        "GetAppointmentsResult_appointmentsItem_doctorId": {
            "type": "string"
        },
        "GetAppointmentsResult_appointmentsItem_patientServiceFee": {
            "type": "string"
        },
        "GetAppointmentsResult_appointmentsItem_serviceId": {
            "type": "string"
        },
        "GetAppointmentsResult_appointmentsItem_totalPrice": {
            "type": "string"
        },
        "GetAppointmentsResult_appointmentsItem_reimbursementDate": {
            "type": "string"
        },
        "GetAppointmentsResult_appointmentsItem_durationSeconds": {
            "type": "string"
        },
        "GetAppointmentsResult_appointmentsItem_chargeId": {
            "type": "string"
        },
        "GetAppointmentsResult_appointmentsItem_id": {
            "type": "string"
        },
        "GetAppointmentsResult_appointmentsItem": {
            "type": "structure",
            "required": [
                "appointmentState",
                "basePrice",
                "chargeId",
                "dateBooked",
                "doctorEarnings",
                "doctorId",
                "doctorServiceFee",
                "durationSeconds",
                "id",
                "patientId",
                "patientServiceFee",
                "serviceId",
                "startTime",
                "totalPrice"
            ],
            "members": {
                "startTime": {
                    "shape": "GetAppointmentsResult_appointmentsItem_startTime"
                },
                "cancellationDate": {
                    "shape": "GetAppointmentsResult_appointmentsItem_cancellationDate"
                },
                "dateBooked": {
                    "shape": "GetAppointmentsResult_appointmentsItem_dateBooked"
                },
                "basePrice": {
                    "shape": "GetAppointmentsResult_appointmentsItem_basePrice"
                },
                "patientId": {
                    "shape": "GetAppointmentsResult_appointmentsItem_patientId"
                },
                "doctorEarnings": {
                    "shape": "GetAppointmentsResult_appointmentsItem_doctorEarnings"
                },
                "doctorServiceFee": {
                    "shape": "GetAppointmentsResult_appointmentsItem_doctorServiceFee"
                },
                "appointmentState": {
                    "shape": "GetAppointmentsResult_appointmentsItem_appointmentState"
                },
                "amountRefunded": {
                    "shape": "GetAppointmentsResult_appointmentsItem_amountRefunded"
                },
                "doctorId": {
                    "shape": "GetAppointmentsResult_appointmentsItem_doctorId"
                },
                "patientServiceFee": {
                    "shape": "GetAppointmentsResult_appointmentsItem_patientServiceFee"
                },
                "serviceId": {
                    "shape": "GetAppointmentsResult_appointmentsItem_serviceId"
                },
                "totalPrice": {
                    "shape": "GetAppointmentsResult_appointmentsItem_totalPrice"
                },
                "reimbursementDate": {
                    "shape": "GetAppointmentsResult_appointmentsItem_reimbursementDate"
                },
                "durationSeconds": {
                    "shape": "GetAppointmentsResult_appointmentsItem_durationSeconds"
                },
                "chargeId": {
                    "shape": "GetAppointmentsResult_appointmentsItem_chargeId"
                },
                "id": {
                    "shape": "GetAppointmentsResult_appointmentsItem_id"
                }
            }
        },
        "GetAppointmentsResult_appointments": {
            "type": "list",
            "member": {
                "shape": "GetAppointmentsResult_appointmentsItem"
            }
        },
        "GetAppointmentsResult_doctorsItem_city": {
            "type": "string"
        },
        "GetAppointmentsResult_doctorsItem_lastName": {
            "type": "string"
        },
        "GetAppointmentsResult_doctorsItem_officeNumber": {
            "type": "string"
        },
        "GetAppointmentsResult_doctorsItem_profilePhotoUrl": {
            "type": "string"
        },
        "GetAppointmentsResult_doctorsItem_servicesOfferedItem": {
            "type": "string"
        },
        "GetAppointmentsResult_doctorsItem_servicesOffered": {
            "type": "list",
            "member": {
                "shape": "GetAppointmentsResult_doctorsItem_servicesOfferedItem"
            }
        },
        "GetAppointmentsResult_doctorsItem_serviceDetailsListItem_doctorId": {
            "type": "string"
        },
        "GetAppointmentsResult_doctorsItem_serviceDetailsListItem_priceDollars": {
            "type": "string"
        },
        "GetAppointmentsResult_doctorsItem_serviceDetailsListItem_durationSeconds": {
            "type": "string"
        },
        "GetAppointmentsResult_doctorsItem_serviceDetailsListItem_serviceId": {
            "type": "string"
        },
        "GetAppointmentsResult_doctorsItem_serviceDetailsListItem": {
            "type": "structure",
            "required": [
                "doctorId",
                "durationSeconds",
                "priceDollars",
                "serviceId"
            ],
            "members": {
                "doctorId": {
                    "shape": "GetAppointmentsResult_doctorsItem_serviceDetailsListItem_doctorId"
                },
                "priceDollars": {
                    "shape": "GetAppointmentsResult_doctorsItem_serviceDetailsListItem_priceDollars"
                },
                "durationSeconds": {
                    "shape": "GetAppointmentsResult_doctorsItem_serviceDetailsListItem_durationSeconds"
                },
                "serviceId": {
                    "shape": "GetAppointmentsResult_doctorsItem_serviceDetailsListItem_serviceId"
                }
            }
        },
        "GetAppointmentsResult_doctorsItem_serviceDetailsList": {
            "type": "list",
            "member": {
                "shape": "GetAppointmentsResult_doctorsItem_serviceDetailsListItem"
            }
        },
        "GetAppointmentsResult_doctorsItem_specialtyId": {
            "type": "string"
        },
        "GetAppointmentsResult_doctorsItem_streetNumberAndName": {
            "type": "string"
        },
        "GetAppointmentsResult_doctorsItem_postalCode": {
            "type": "string"
        },
        "GetAppointmentsResult_doctorsItem_administrativeAreaL1": {
            "type": "string"
        },
        "GetAppointmentsResult_doctorsItem_coverPhotoUrl": {
            "type": "string"
        },
        "GetAppointmentsResult_doctorsItem_payoutInfoIsSet": {
            "type": "boolean"
        },
        "GetAppointmentsResult_doctorsItem_firstName": {
            "type": "string"
        },
        "GetAppointmentsResult_doctorsItem_longitude": {
            "type": "double"
        },
        "GetAppointmentsResult_doctorsItem_suite": {
            "type": "string"
        },
        "GetAppointmentsResult_doctorsItem_id": {
            "type": "string"
        },
        "GetAppointmentsResult_doctorsItem_latitude": {
            "type": "double"
        },
        "GetAppointmentsResult_doctorsItem": {
            "type": "structure",
            "required": [
                "firstName",
                "id",
                "lastName",
                "payoutInfoIsSet",
                "servicesOffered",
                "specialtyId"
            ],
            "members": {
                "city": {
                    "shape": "GetAppointmentsResult_doctorsItem_city"
                },
                "lastName": {
                    "shape": "GetAppointmentsResult_doctorsItem_lastName"
                },
                "officeNumber": {
                    "shape": "GetAppointmentsResult_doctorsItem_officeNumber"
                },
                "profilePhotoUrl": {
                    "shape": "GetAppointmentsResult_doctorsItem_profilePhotoUrl"
                },
                "servicesOffered": {
                    "shape": "GetAppointmentsResult_doctorsItem_servicesOffered"
                },
                "serviceDetailsList": {
                    "shape": "GetAppointmentsResult_doctorsItem_serviceDetailsList"
                },
                "specialtyId": {
                    "shape": "GetAppointmentsResult_doctorsItem_specialtyId"
                },
                "streetNumberAndName": {
                    "shape": "GetAppointmentsResult_doctorsItem_streetNumberAndName"
                },
                "postalCode": {
                    "shape": "GetAppointmentsResult_doctorsItem_postalCode"
                },
                "administrativeAreaL1": {
                    "shape": "GetAppointmentsResult_doctorsItem_administrativeAreaL1"
                },
                "coverPhotoUrl": {
                    "shape": "GetAppointmentsResult_doctorsItem_coverPhotoUrl"
                },
                "payoutInfoIsSet": {
                    "shape": "GetAppointmentsResult_doctorsItem_payoutInfoIsSet"
                },
                "firstName": {
                    "shape": "GetAppointmentsResult_doctorsItem_firstName"
                },
                "longitude": {
                    "shape": "GetAppointmentsResult_doctorsItem_longitude"
                },
                "suite": {
                    "shape": "GetAppointmentsResult_doctorsItem_suite"
                },
                "id": {
                    "shape": "GetAppointmentsResult_doctorsItem_id"
                },
                "latitude": {
                    "shape": "GetAppointmentsResult_doctorsItem_latitude"
                }
            }
        },
        "GetAppointmentsResult_doctors": {
            "type": "list",
            "member": {
                "shape": "GetAppointmentsResult_doctorsItem"
            }
        },
        "GetAppointmentsResult_patientsItem_profilePhotoUrl": {
            "type": "string"
        },
        "GetAppointmentsResult_patientsItem_lastName": {
            "type": "string"
        },
        "GetAppointmentsResult_patientsItem_mobileNumber": {
            "type": "string"
        },
        "GetAppointmentsResult_patientsItem_firstName": {
            "type": "string"
        },
        "GetAppointmentsResult_patientsItem_id": {
            "type": "string"
        },
        "GetAppointmentsResult_patientsItem": {
            "type": "structure",
            "required": [
                "firstName",
                "id",
                "lastName",
                "mobileNumber"
            ],
            "members": {
                "profilePhotoUrl": {
                    "shape": "GetAppointmentsResult_patientsItem_profilePhotoUrl"
                },
                "lastName": {
                    "shape": "GetAppointmentsResult_patientsItem_lastName"
                },
                "mobileNumber": {
                    "shape": "GetAppointmentsResult_patientsItem_mobileNumber"
                },
                "firstName": {
                    "shape": "GetAppointmentsResult_patientsItem_firstName"
                },
                "id": {
                    "shape": "GetAppointmentsResult_patientsItem_id"
                }
            }
        },
        "GetAppointmentsResult_patients": {
            "type": "list",
            "member": {
                "shape": "GetAppointmentsResult_patientsItem"
            }
        },
        "GetAppointmentsResult": {
            "type": "structure",
            "required": [
                "appointments"
            ],
            "members": {
                "appointments": {
                    "shape": "GetAppointmentsResult_appointments"
                },
                "doctors": {
                    "shape": "GetAppointmentsResult_doctors"
                },
                "patients": {
                    "shape": "GetAppointmentsResult_patients"
                }
            }
        },
        "ClientAppointmentBill_version": {
            "type": "string"
        },
        "ClientAppointmentBill_patientServiceFee": {
            "type": "string"
        },
        "ClientAppointmentBill_doctorServiceFee": {
            "type": "string"
        },
        "ClientAppointmentBill_totalPrice": {
            "type": "string"
        },
        "ClientAppointmentBill_basePrice": {
            "type": "string"
        },
        "ClientAppointmentBill": {
            "type": "structure",
            "required": [
                "basePrice",
                "doctorServiceFee",
                "patientServiceFee",
                "totalPrice",
                "version"
            ],
            "members": {
                "version": {
                    "shape": "ClientAppointmentBill_version"
                },
                "patientServiceFee": {
                    "shape": "ClientAppointmentBill_patientServiceFee"
                },
                "doctorServiceFee": {
                    "shape": "ClientAppointmentBill_doctorServiceFee"
                },
                "totalPrice": {
                    "shape": "ClientAppointmentBill_totalPrice"
                },
                "basePrice": {
                    "shape": "ClientAppointmentBill_basePrice"
                }
            }
        },
        "UrlForFileRequest_patientId": {
            "type": "string"
        },
        "UrlForFileRequest_httpMethod": {
            "type": "string"
        },
        "UrlForFileRequest_doctorId": {
            "type": "string"
        },
        "UrlForFileRequest_fileName": {
            "type": "string"
        },
        "UrlForFileRequest": {
            "type": "structure",
            "required": [
                "fileName",
                "httpMethod"
            ],
            "members": {
                "patientId": {
                    "shape": "UrlForFileRequest_patientId"
                },
                "httpMethod": {
                    "shape": "UrlForFileRequest_httpMethod"
                },
                "doctorId": {
                    "shape": "UrlForFileRequest_doctorId"
                },
                "fileName": {
                    "shape": "UrlForFileRequest_fileName"
                }
            }
        },
        "SetDefaultPaymentSourceRequest_paymentMethodId": {
            "type": "string"
        },
        "SetDefaultPaymentSourceRequest": {
            "type": "structure",
            "required": [],
            "members": {
                "paymentMethodId": {
                    "shape": "SetDefaultPaymentSourceRequest_paymentMethodId"
                }
            }
        }
    }
}
